verifone/__init__.py
verifone/verifone.py
verifone-0.1.22.dist-info/AUTHORS.rst
verifone-0.1.22.dist-info/LICENSE
verifone-0.1.22.dist-info/METADATA
verifone-0.1.22.dist-info/WHEEL
verifone-0.1.22.dist-info/top_level.txt
verifone-0.1.22.dist-info/RECORD
