Metadata-Version: 2.1
Name: verifone
Version: 0.1.22
Summary: Python package for Verifone
Home-page: https://github.com/vilkasgroup/Verifone
Author: Jaana Sarajärvi
Author-email: jaana.sarajarvi@vilkas.fi
License: MIT license
Keywords: verifone
Platform: UNKNOWN
Classifier: Development Status :: 2 - Pre-Alpha
Classifier: Intended Audience :: Developers
Classifier: License :: OSI Approved :: MIT License
Classifier: Natural Language :: English
Classifier: Programming Language :: Python :: 2.7
Classifier: Programming Language :: Python :: 3.6
Classifier: Programming Language :: Python :: 3.7
Requires-Dist: requests (>=2.7.0)
Requires-Dist: pycountry (>=18.5.26)
Requires-Dist: pycryptodome (>=3.6.6)
